smalldi/__init__.py
smalldi/annotation.py
smalldi/py.typed
smalldi/wrappers.py
smalldi-0.1.1.dist-info/METADATA
smalldi-0.1.1.dist-info/WHEEL
smalldi-0.1.1.dist-info/licenses/LICENSE
smalldi-0.1.1.dist-info/RECORD
