Metadata-Version: 2.4
Name: smalldi
Version: 0.1.1
Summary: Small, annotation-driven dependency injection for Python.
Project-URL: Homepage, https://github.com/0xf104a/smalldi
Project-URL: Documentation, https://github.com/0xf104a/smalldi#readme
Project-URL: Source, https://github.com/0xf104a/smalldi
Project-URL: Issues, https://github.com/0xf104a/smalldi/issues
Author-email: Anna-Sofia Kasierocka <f104a@f104a.io>
License: MIT License
License-File: LICENSE
Keywords: annotations,dependency injection,di,typing
Classifier: Development Status :: 4 - Beta
Classifier: Intended Audience :: Developers
Classifier: License :: OSI Approved :: MIT License
Classifier: Programming Language :: Python
Classifier: Programming Language :: Python :: 3
Classifier: Programming Language :: Python :: 3 :: Only
Classifier: Programming Language :: Python :: 3.11
Classifier: Programming Language :: Python :: 3.12
Classifier: Programming Language :: Python :: 3.13
Classifier: Topic :: Software Development :: Libraries
Classifier: Typing :: Typed
Requires-Python: >=3.11
Requires-Dist: typing-extensions>=4.5; python_version >= '3.11'
